mkdocs_decodiff_plugin/__init__.py
mkdocs_decodiff_plugin/decodiff.py
mkdocs_decodiff_plugin/markdown_marker.py
mkdocs_decodiff_plugin/_git_diff/__init__.py
mkdocs_decodiff_plugin/_git_diff/git_diff.py
mkdocs_decodiff_plugin/_git_diff/parse_porcelain_diff.py
mkdocs_decodiff_plugin/_git_diff/parse_unified_diff.py
mkdocs_decodiff_plugin/mkdocs_plugin/__init__.py
mkdocs_decodiff_plugin/mkdocs_plugin/plugin.py
mkdocs_decodiff_plugin/mkdocs_plugin/assets/decodiff.css
mkdocs_decodiff_plugin-0.0.5.dist-info/licenses/LICENSE
mkdocs_decodiff_plugin-0.0.5.dist-info/METADATA
mkdocs_decodiff_plugin-0.0.5.dist-info/WHEEL
mkdocs_decodiff_plugin-0.0.5.dist-info/entry_points.txt
mkdocs_decodiff_plugin-0.0.5.dist-info/top_level.txt
mkdocs_decodiff_plugin-0.0.5.dist-info/RECORD
