Metadata-Version: 2.4
Name: mkdocs-decodiff-plugin
Version: 0.0.5
Summary: MkDocs plugin to decorate git diff lines
Author-email: kkAyataka <kk.ayataka@gmail.com>
License-Expression: MIT
Project-URL: Homepage, https://github.com/kkAyataka/mkdocs-decodiff-plugin
Project-URL: Issues, https://github.com/kkAyataka/mkdocs-decodiff-plugin
Classifier: Development Status :: 4 - Beta
Classifier: Programming Language :: Python :: 3
Classifier: Operating System :: OS Independent
Requires-Python: >=3.9
License-File: LICENSE
Provides-Extra: dev
Requires-Dist: build; extra == "dev"
Requires-Dist: twine; extra == "dev"
Requires-Dist: wheel; extra == "dev"
Requires-Dist: pytest; extra == "dev"
Requires-Dist: pytest-cov; extra == "dev"
Requires-Dist: ruff; extra == "dev"
Requires-Dist: watchdog; extra == "dev"
Requires-Dist: mkdocs; extra == "dev"
Dynamic: license-file
